dscience/__init__.py
dscience/full.py
dscience/j.py
dscience/analysis/__init__.py
dscience/analysis/morphology.py
dscience/analysis/peak_finding.py
dscience/analysis/stats.py
dscience/biochem/__init__.py
dscience/biochem/atc_tree.py
dscience/biochem/multiwell_plate_rois.py
dscience/biochem/multiwell_plates.py
dscience/biochem/tissue_expression.py
dscience/biochem/uniprot_go.py
dscience/core/__init__.py
dscience/core/abcd.py
dscience/core/chars.py
dscience/core/exceptions.py
dscience/core/extended_df.py
dscience/core/hasher.py
dscience/core/internal.py
dscience/core/io.py
dscience/core/iterators.py
dscience/core/messages.py
dscience/core/mocks.py
dscience/core/web_resource.py
dscience/ml/__init__.py
dscience/ml/accuracy_frame.py
dscience/ml/classifier_path.py
dscience/ml/confusion_matrix.py
dscience/ml/decision_frame.py
dscience/ml/sklearn_utils.py
dscience/ml/trainable.py
dscience/support/__init__.py
dscience/support/connection.py
dscience/support/df_mem_cache.py
dscience/support/fancy_console.py
dscience/support/fancy_logger.py
dscience/support/flexible_logger.py
dscience/support/log_format.py
dscience/support/magic_template.py
dscience/support/plot_ticks.py
dscience/support/py_dependencies.py
dscience/support/time_unit.py
dscience/support/toml_data.py
dscience/tools/__init__.py
dscience/tools/base_tools.py
dscience/tools/call_tools.py
dscience/tools/common_tools.py
dscience/tools/console_tools.py
dscience/tools/filesys_tools.py
dscience/tools/loop_tools.py
dscience/tools/numeric_tools.py
dscience/tools/pandas_tools.py
dscience/tools/path_tools.py
dscience/tools/program_tools.py
dscience/tools/string_tools.py
dscience/tools/unit_tools.py
dscience-0.0.1.dist-info/LICENSE
dscience-0.0.1.dist-info/METADATA
dscience-0.0.1.dist-info/WHEEL
dscience-0.0.1.dist-info/top_level.txt
dscience-0.0.1.dist-info/RECORD
