Metadata-Version: 2.1
Name: dscience
Version: 0.0.1
Summary: A collection of Python snippets for the Kokel Lab
Home-page: https://github.com/kokellab/dscience
Author: Douglas Myers-Turnbull
Maintainer: Douglas Myers-Turnbull
License: Apache 2.0
Download-URL: https://github.com/kokellab/dscience/archive/0.0.1.tar.gz
Project-URL: package, https://pypi.org/project/dscience
Project-URL: build, https://travis-ci.org/kokellab/dscience
Project-URL: docs, https://dscience.readthedocs.io
Project-URL: source, https://github.com/kokellab/dscience
Project-URL: issues, https://github.com/kokellab/dscience/issues
Keywords: utilities,data science,pandas
Platform: UNKNOWN
Classifier: Development Status :: 3 - Alpha
Classifier: Intended Audience :: Developers
Classifier: Natural Language :: English
Classifier: License :: OSI Approved :: Apache Software License
Classifier: Programming Language :: Python :: 3 :: Only
Classifier: Programming Language :: Python :: 3.7
Classifier: Programming Language :: Python :: 3.8
Classifier: Topic :: Software Development :: Libraries :: Python Modules
Classifier: Topic :: Scientific/Engineering :: Bio-Informatics
Classifier: Topic :: Scientific/Engineering :: Artificial Intelligence
Classifier: Operating System :: OS Independent
Classifier: Typing :: Typed
Requires-Python: >=3.7,<3.9
Requires-Dist: dill (<1.0,>=0.3)
Requires-Dist: jsonpickle (<2.0,>=1.3)
Requires-Dist: natsort (<8.0,>=7.0)
Requires-Dist: numpy (<2.0,>=1.18)
Requires-Dist: pandas (<2.0,>=1.0)
Requires-Dist: requests (<3.0,>=2.23)
Provides-Extra: all
Requires-Dist: colorama (<1.0,>=0.4.3) ; extra == 'all'
Requires-Dist: deprecated (<2.0,>=1.2) ; extra == 'all'
Requires-Dist: overrides (<3.0,>=2.8) ; extra == 'all'
Requires-Dist: psutil (<6.0,>=5.7) ; extra == 'all'
Requires-Dist: toml (<1.0,>=0.10) ; extra == 'all'
Requires-Dist: PyMySQL (<1.0,>=0.9) ; extra == 'all'
Requires-Dist: peewee (<4.0,>=3.13) ; extra == 'all'
Requires-Dist: sshtunnel (<1.0,>=0.1.5) ; extra == 'all'
Requires-Dist: joblib (<1.0,>=0.14) ; extra == 'all'
Requires-Dist: matplotlib (<4.0,>=3.2) ; extra == 'all'
Requires-Dist: scikit-image (<1.0,>=0.16) ; extra == 'all'
Requires-Dist: scikit-learn (<1.0,>=0.22) ; extra == 'all'
Requires-Dist: scipy (<2.0,>=1.4) ; extra == 'all'
Requires-Dist: ipython (<8.0,>=7.13) ; extra == 'all'
Requires-Dist: hypothesis (<6.0,>=5.8) ; extra == 'all'
Requires-Dist: pytest (<6.0,>=5.4) ; extra == 'all'
Requires-Dist: goatools (<2.0,>=1.0) ; extra == 'all'
Requires-Dist: uniprot (<2.0,>=1.3) ; extra == 'all'
Provides-Extra: biochem
Requires-Dist: goatools (<2.0,>=1.0) ; extra == 'biochem'
Requires-Dist: uniprot (<2.0,>=1.3) ; extra == 'biochem'
Provides-Extra: db
Requires-Dist: PyMySQL (<1.0,>=0.9) ; extra == 'db'
Requires-Dist: peewee (<4.0,>=3.13) ; extra == 'db'
Requires-Dist: sshtunnel (<1.0,>=0.1.5) ; extra == 'db'
Provides-Extra: extra
Requires-Dist: colorama (<1.0,>=0.4.3) ; extra == 'extra'
Requires-Dist: deprecated (<2.0,>=1.2) ; extra == 'extra'
Requires-Dist: overrides (<3.0,>=2.8) ; extra == 'extra'
Requires-Dist: psutil (<6.0,>=5.7) ; extra == 'extra'
Requires-Dist: toml (<1.0,>=0.10) ; extra == 'extra'
Provides-Extra: jupyter
Requires-Dist: ipython (<8.0,>=7.13) ; extra == 'jupyter'
Provides-Extra: numeric
Requires-Dist: joblib (<1.0,>=0.14) ; extra == 'numeric'
Requires-Dist: matplotlib (<4.0,>=3.2) ; extra == 'numeric'
Requires-Dist: scikit-image (<1.0,>=0.16) ; extra == 'numeric'
Requires-Dist: scikit-learn (<1.0,>=0.22) ; extra == 'numeric'
Requires-Dist: scipy (<2.0,>=1.4) ; extra == 'numeric'
Provides-Extra: test
Requires-Dist: hypothesis (<6.0,>=5.8) ; extra == 'test'
Requires-Dist: pytest (<6.0,>=5.4) ; extra == 'test'
